autofunccli/__init__.py
autofunccli/analysis.py
autofunccli/cmdclass.py
autofunccli-1.0.6.dist-info/LICENSE
autofunccli-1.0.6.dist-info/METADATA
autofunccli-1.0.6.dist-info/WHEEL
autofunccli-1.0.6.dist-info/top_level.txt
autofunccli-1.0.6.dist-info/RECORD
