Metadata-Version: 2.1
Name: autofunccli
Version: 1.0.6
Summary: Transform your function into a command line utility.
Home-page: https://github.com/CuadrosNicolas/Python-Command-Function
Author: Nicolas Cuadros
Author-email: cuadros.nicolas@orange.fr
License: UNKNOWN
Platform: UNKNOWN
Classifier: Programming Language :: Python :: 3
Classifier: License :: OSI Approved :: MIT License
Classifier: Operating System :: OS Independent
Requires-Python: >=3.6
